LICENSE
MANIFEST.in
README.md
READMErst.txt
setup.py
pyilchimp/__init__.py
pyilchimp/mailchimp_manager.py
pyilchimp.egg-info/PKG-INFO
pyilchimp.egg-info/SOURCES.txt
pyilchimp.egg-info/dependency_links.txt
pyilchimp.egg-info/not-zip-safe
pyilchimp.egg-info/requires.txt
pyilchimp.egg-info/top_level.txt