Metadata-Version: 1.1
Name: pyilchimp
Version: 0.1.1
Summary: Wrapper library for Mailchimp's 3.0 API
Home-page: https://github.com/Antman261/pyilchimp
Author: Anthony Manning-Franklin
Author-email: anthony.manning.franklin@gmail.com.com
License: MIT
Keywords: API RESTful wrapper Mailchimp EDM
Platform: UNKNOWN
Classifier: Intended Audience :: Developers
Classifier: License :: OSI Approved :: MIT License
Classifier: Programming Language :: Python :: 2
Classifier: Programming Language :: Python :: 2.7
Classifier: Programming Language :: Python :: 3
Classifier: Programming Language :: Python :: 3.1
Classifier: Programming Language :: Python :: 3.2
Classifier: Programming Language :: Python :: 3.3
Classifier: Programming Language :: Python :: 3.4
Classifier: Programming Language :: Python :: 3.5
